[
  {
    "bucket": ">$4.040",
    "ticker": "KXAAAGASW-26MAR30-4.040",
    "side": "YES",
    "limit_price_c": 4,
    "current_bid_c": 4,
    "current_ask_c": 5,
    "p_model": 34.1,
    "edge_pp": 30.1,
    "ev_if_filled_c": 30.05,
    "contracts": 1243,
    "kelly_full": 0.3132,
    "kelly_scaled": 0.3132
  },
  {
    "bucket": ">$4.060",
    "ticker": "KXAAAGASW-26MAR30-4.060",
    "side": "YES",
    "limit_price_c": 3,
    "current_bid_c": 3,
    "current_ask_c": 4,
    "p_model": 29.8,
    "edge_pp": 26.8,
    "ev_if_filled_c": 26.76,
    "contracts": 1457,
    "kelly_full": 0.276,
    "kelly_scaled": 0.276
  },
  {
    "bucket": ">$4.020",
    "ticker": "KXAAAGASW-26MAR30-4.020",
    "side": "YES",
    "limit_price_c": 13,
    "current_bid_c": 12,
    "current_ask_c": 16,
    "p_model": 38.6,
    "edge_pp": 25.6,
    "ev_if_filled_c": 25.39,
    "contracts": 357,
    "kelly_full": 0.2925,
    "kelly_scaled": 0.2925
  },
  {
    "bucket": ">$4.080",
    "ticker": "KXAAAGASW-26MAR30-4.080",
    "side": "YES",
    "limit_price_c": 2,
    "current_bid_c": 2,
    "current_ask_c": 3,
    "p_model": 25.9,
    "edge_pp": 24.0,
    "ev_if_filled_c": 23.91,
    "contracts": 1932,
    "kelly_full": 0.2441,
    "kelly_scaled": 0.2441
  },
  {
    "bucket": ">$4.100",
    "ticker": "KXAAAGASW-26MAR30-4.100",
    "side": "YES",
    "limit_price_c": 2,
    "current_bid_c": 2,
    "current_ask_c": 3,
    "p_model": 22.3,
    "edge_pp": 20.3,
    "ev_if_filled_c": 20.28,
    "contracts": 1639,
    "kelly_full": 0.207,
    "kelly_scaled": 0.207
  },
  {
    "bucket": ">$4.120",
    "ticker": "KXAAAGASW-26MAR30-4.120",
    "side": "YES",
    "limit_price_c": 1,
    "current_bid_c": 1,
    "current_ask_c": 2,
    "p_model": 19.0,
    "edge_pp": 18.0,
    "ev_if_filled_c": 17.95,
    "contracts": 2872,
    "kelly_full": 0.1813,
    "kelly_scaled": 0.1813
  },
  {
    "bucket": ">$4.140",
    "ticker": "KXAAAGASW-26MAR30-4.140",
    "side": "YES",
    "limit_price_c": 1,
    "current_bid_c": 1,
    "current_ask_c": 2,
    "p_model": 16.1,
    "edge_pp": 15.1,
    "ev_if_filled_c": 15.1,
    "contracts": 2416,
    "kelly_full": 0.1526,
    "kelly_scaled": 0.1526
  },
  {
    "bucket": ">$4.160",
    "ticker": "KXAAAGASW-26MAR30-4.160",
    "side": "YES",
    "limit_price_c": 1,
    "current_bid_c": 0,
    "current_ask_c": 2,
    "p_model": 13.5,
    "edge_pp": 12.5,
    "ev_if_filled_c": 12.44,
    "contracts": 1990,
    "kelly_full": 0.1257,
    "kelly_scaled": 0.1257
  },
  {
    "bucket": ">$4.180",
    "ticker": "KXAAAGASW-26MAR30-4.180",
    "side": "YES",
    "limit_price_c": 1,
    "current_bid_c": 1,
    "current_ask_c": 2,
    "p_model": 10.9,
    "edge_pp": 9.9,
    "ev_if_filled_c": 9.86,
    "contracts": 1577,
    "kelly_full": 0.0996,
    "kelly_scaled": 0.0996
  },
  {
    "bucket": ">$4.200",
    "ticker": "KXAAAGASW-26MAR30-4.200",
    "side": "YES",
    "limit_price_c": 1,
    "current_bid_c": 0,
    "current_ask_c": 2,
    "p_model": 8.7,
    "edge_pp": 7.7,
    "ev_if_filled_c": 7.69,
    "contracts": 1230,
    "kelly_full": 0.0777,
    "kelly_scaled": 0.0777
  },
  {
    "bucket": ">$4.220",
    "ticker": "KXAAAGASW-26MAR30-4.220",
    "side": "YES",
    "limit_price_c": 1,
    "current_bid_c": 0,
    "current_ask_c": 2,
    "p_model": 6.9,
    "edge_pp": 5.9,
    "ev_if_filled_c": 5.88,
    "contracts": 940,
    "kelly_full": 0.0594,
    "kelly_scaled": 0.0594
  },
  {
    "bucket": ">$4.240",
    "ticker": "KXAAAGASW-26MAR30-4.240",
    "side": "YES",
    "limit_price_c": 1,
    "current_bid_c": 0,
    "current_ask_c": 2,
    "p_model": 5.5,
    "edge_pp": 4.5,
    "ev_if_filled_c": 4.44,
    "contracts": 710,
    "kelly_full": 0.0449,
    "kelly_scaled": 0.0449
  },
  {
    "bucket": ">$4.260",
    "ticker": "KXAAAGASW-26MAR30-4.260",
    "side": "YES",
    "limit_price_c": 1,
    "current_bid_c": 1,
    "current_ask_c": 2,
    "p_model": 4.2,
    "edge_pp": 3.2,
    "ev_if_filled_c": 3.23,
    "contracts": 516,
    "kelly_full": 0.0326,
    "kelly_scaled": 0.0326
  }
]